README.txt
setup.py
pyworked/__init__.py
pyworked.egg-info/PKG-INFO
pyworked.egg-info/SOURCES.txt
pyworked.egg-info/dependency_links.txt
pyworked.egg-info/not-zip-safe
pyworked.egg-info/requires.txt
pyworked.egg-info/top_level.txt
pyworked/modules/__init__.py
pyworked/modules/base_algorithms.py
pyworked/modules/binary_search.py
pyworked/modules/calc.py
pyworked/modules/code.py
pyworked/modules/elevation.py
pyworked/modules/er_sieve.py
pyworked/modules/factorial.py
pyworked/modules/fib.py
pyworked/modules/hash.py
pyworked/modules/linear_search.py
pyworked/modules/nod.py
pyworked/modules/password_generator.py
pyworked/modules/prime_or_not_prime.py
pyworked/modules/sort_to_high.py
pyworked/modules/sort_to_low.py
pyworked/modules/weather.py
pyworked/modules/web_server.py