Metadata-Version: 1.1
Name: pyworked
Version: 0.2.7
Summary: The easiest library for Python 3
Home-page: https://github.com/Onebet163/pywork
Author: Onebet163, UnAnsav
Author-email: Yandancheats@gmail.com
License: MIT
Keywords: library python pywork py work worked pyworked
Platform: UNKNOWN
Classifier: Development Status :: 3 - Alpha
Classifier: License :: OSI Approved :: MIT License
Classifier: Programming Language :: Python :: 3.8
